Workbook

Sheet Guide
A1: LinkedIn Ads Reporting Template
A2: Dedicated LinkedIn Ads report. Green-themed, formula-driven, plug-and-play. Fill one tab a month, or let Claude pull it. Full steps and prompts are on the Instructions & Prompts tab.
A4: How this works
A5: Account Summary is your single source of truth. Fill one row per month. The Executive Summary and Month-on-Month tabs read from it and recompute on their own.
A6: Blue cells are where you type. Grey cells are formulas. Leave the formulas alone.
A7: Percentages are stored as values. 0.5% is held as 0.005.
A9: Leads need a manual step
A10: LinkedIn lead-gen form leads are not available through the data connector. Pull them from Campaign Manager (the Leads column, or Account Assets, Lead Gen Forms) or your CRM, and type them into the blue Leads column.
A12: Tabs
A13: Instructions & Prompts, Account Summary, Executive Summary, Month-on-Month, By Campaign, By Campaign Group, By Objective, Engagement, Budget Pacing, Flags & Fixes, Definitions, Sources.
A14: Start on the Instructions & Prompts tab. It has the full steps and the Claude prompts for every tab.

Sheet Instructions & Prompts
A1: Instructions & Prompts
A2: Everything you need to fill this workbook, including the exact prompts to paste into Claude. No external docs needed.
A4: How this workbook works
A5: Account Summary is the single source of truth. Fill one row per month and the Executive Summary, Month-on-Month, and the rest read from it. Blue cells are inputs. Grey cells are formulas. Percentages are stored as values, so 0.5% is 0.005.
A7: The fast way: let Claude pull the data
A8: LinkedIn Ads connects to Claude through the Windsor.ai connector. Turn it on in Claude, confirm your account, then paste the prompts below one at a time. Replace <LINKEDIN-ADS-ID> with your account ID the first time.
A10: Step 1. Connect and confirm
A11: Using the Windsor.ai connector, list my connected accounts and show me my LinkedIn Ads account ID.
A13: Step 2. Account Summary (fill this first)
A14: From LinkedIn Ads <LINKEDIN-ADS-ID>, give me spend, impressions, clicks, and engagement rate by month for the last 12 months. Lay it out as one row per month for the Account Summary tab. I will add lead-gen form leads myself.
A16: Step 3. By Campaign
A17: From LinkedIn Ads <LINKEDIN-ADS-ID>, one row per campaign per month for the last 6 months: campaign group name, objective type, impressions, clicks, spend, conversions, engagement rate.
... A38: LinkedIn is a premium channel: high CPM and CPC are normal, so judge it on cost per lead and lead quality, not CPC. Watch frequency and creative fatigue, keep audiences above a few hundred thousand, and make sure your lead forms are short. The Flags & Fixes tab lists the usual problems and the fix for each.

Sheet Account Summary
A1: Account Summary
A2: One row per month. Blue cells are inputs (Leads come from Campaign Manager or your CRM). CTR, CPC, CPM, cost per lead, and lead rate are formulas. This tab feeds the Executive Summary and Month-on-Month.
A4: Month | B4: Spend | C4: Impressions | D4: Clicks | E4: CTR | F4: Avg CPC | G4: CPM | H4: Leads | I4: Cost / Lead | J4: Lead Rate | K4: Engagement Rate | L4: Conversions
A5: Month 1 | B5: 6000 | C5: 320000 | D5: 1600 | E5: =IF(OR(C5="",C5=0),"",D5/C5) -> 0.005 | F5: =IF(OR(D5="",D5=0),"",B5/D5) -> 3.75 | G5: =IF(OR(C5="",C5=0),"",B5/C5*1000) -> 18.75 | H5: 40 | I5: =IF(OR(H5="",H5=0),"",B5/H5) -> 150 | J5: =IF(OR(D5="",D5=0),"",H5/D5) -> 0.025 | K5: 0.018 | L5: 12
A6: Month 2 | B6: 7200 | C6: 360000 | D6: 1980 | E6: =IF(OR(C6="",C6=0),"",D6/C6) -> 0.0055 | F6: =IF(OR(D6="",D6=0),"",B6/D6) -> 3.6363636 | G6: =IF(OR(C6="",C6=0),"",B6/C6*1000) -> 20 | H6: 52 | I6: =IF(OR(H6="",H6=0),"",B6/H6) -> 138.46154 | J6: =IF(OR(D6="",D6=0),"",H6/D6) -> 0.026262626 | K6: 0.02 | L6: 16
A7: Month 3 | B7: 8500 | C7: 410000 | D7: 2300 | E7: =IF(OR(C7="",C7=0),"",D7/C7) -> 0.0056097561 | F7: =IF(OR(D7="",D7=0),"",B7/D7) -> 3.6956522 | G7: =IF(OR(C7="",C7=0),"",B7/C7*1000) -> 20.731707 | H7: 63 | I7: =IF(OR(H7="",H7=0),"",B7/H7) -> 134.92063 | J7: =IF(OR(D7="",D7=0),"",H7/D7) -> 0.027391304 | K7: 0.021 | L7: 20
A8: Month 4 | E8: =IF(OR(C8="",C8=0),"",D8/C8) | F8: =IF(OR(D8="",D8=0),"",B8/D8) | G8: =IF(OR(C8="",C8=0),"",B8/C8*1000) | I8: =IF(OR(H8="",H8=0),"",B8/H8) | J8: =IF(OR(D8="",D8=0),"",H8/D8)
A9: Month 5 | E9: =IF(OR(C9="",C9=0),"",D9/C9) | F9: =IF(OR(D9="",D9=0),"",B9/D9) | G9: =IF(OR(C9="",C9=0),"",B9/C9*1000) | I9: =IF(OR(H9="",H9=0),"",B9/H9) | J9: =IF(OR(D9="",D9=0),"",H9/D9)
A10: Month 6 | E10: =IF(OR(C10="",C10=0),"",D10/C10) | F10: =IF(OR(D10="",D10=0),"",B10/D10) | G10: =IF(OR(C10="",C10=0),"",B10/C10*1000) | I10: =IF(OR(H10="",H10=0),"",B10/H10) | J10: =IF(OR(D10="",D10=0),"",H10/D10)
A11: Month 7 | E11: =IF(OR(C11="",C11=0),"",D11/C11) | F11: =IF(OR(D11="",D11=0),"",B11/D11) | G11: =IF(OR(C11="",C11=0),"",B11/C11*1000) | I11: =IF(OR(H11="",H11=0),"",B11/H11) | J11: =IF(OR(D11="",D11=0),"",H11/D11)
A12: Month 8 | E12: =IF(OR(C12="",C12=0),"",D12/C12) | F12: =IF(OR(D12="",D12=0),"",B12/D12) | G12: =IF(OR(C12="",C12=0),"",B12/C12*1000) | I12: =IF(OR(H12="",H12=0),"",B12/H12) | J12: =IF(OR(D12="",D12=0),"",H12/D12)
A13: Month 9 | E13: =IF(OR(C13="",C13=0),"",D13/C13) | F13: =IF(OR(D13="",D13=0),"",B13/D13) | G13: =IF(OR(C13="",C13=0),"",B13/C13*1000) | I13: =IF(OR(H13="",H13=0),"",B13/H13) | J13: =IF(OR(D13="",D13=0),"",H13/D13)
A14: Month 10 | E14: =IF(OR(C14="",C14=0),"",D14/C14) | F14: =IF(OR(D14="",D14=0),"",B14/D14) | G14: =IF(OR(C14="",C14=0),"",B14/C14*1000) | I14: =IF(OR(H14="",H14=0),"",B14/H14) | J14: =IF(OR(D14="",D14=0),"",H14/D14)
A15: Month 11 | E15: =IF(OR(C15="",C15=0),"",D15/C15) | F15: =IF(OR(D15="",D15=0),"",B15/D15) | G15: =IF(OR(C15="",C15=0),"",B15/C15*1000) | I15: =IF(OR(H15="",H15=0),"",B15/H15) | J15: =IF(OR(D15="",D15=0),"",H15/D15)
A16: Month 12 | E16: =IF(OR(C16="",C16=0),"",D16/C16) | F16: =IF(OR(D16="",D16=0),"",B16/D16) | G16: =IF(OR(C16="",C16=0),"",B16/C16*1000) | I16: =IF(OR(H16="",H16=0),"",B16/H16) | J16: =IF(OR(D16="",D16=0),"",H16/D16)
A17: Month 13 | E17: =IF(OR(C17="",C17=0),"",D17/C17) | F17: =IF(OR(D17="",D17=0),"",B17/D17) | G17: =IF(OR(C17="",C17=0),"",B17/C17*1000) | I17: =IF(OR(H17="",H17=0),"",B17/H17) | J17: =IF(OR(D17="",D17=0),"",H17/D17)
A18: Month 14 | E18: =IF(OR(C18="",C18=0),"",D18/C18) | F18: =IF(OR(D18="",D18=0),"",B18/D18) | G18: =IF(OR(C18="",C18=0),"",B18/C18*1000) | I18: =IF(OR(H18="",H18=0),"",B18/H18) | J18: =IF(OR(D18="",D18=0),"",H18/D18)
A19: Month 15 | E19: =IF(OR(C19="",C19=0),"",D19/C19) | F19: =IF(OR(D19="",D19=0),"",B19/D19) | G19: =IF(OR(C19="",C19=0),"",B19/C19*1000) | I19: =IF(OR(H19="",H19=0),"",B19/H19) | J19: =IF(OR(D19="",D19=0),"",H19/D19)
... A28: Month 24 | E28: =IF(OR(C28="",C28=0),"",D28/C28) | F28: =IF(OR(D28="",D28=0),"",B28/D28) | G28: =IF(OR(C28="",C28=0),"",B28/C28*1000) | I28: =IF(OR(H28="",H28=0),"",B28/H28) | J28: =IF(OR(D28="",D28=0),"",H28/D28)
A30: Fill the blue cells each month, including Leads from Campaign Manager. LinkedIn runs expensive, so the metric that matters is cost per lead, not CPC. If cost per lead climbs, look at audience size, creative fatigue, and lead-form length before adding budget.

Sheet Executive Summary
A1: Executive Summary | P1: =IFERROR(MATCH($B$4,'Account Summary'!$A$5:$A$28,0),1) -> 3
A2: Pick a month. The cards show that month versus the one before it. Everything reads from Account Summary.
A4: Pick a month: | B4: Month 3
A6: Metric | B6: Selected month | C6: Prior month | D6: Change
A7: Spend | B7: =IFERROR(INDEX('Account Summary'!$B$5:$B$28,$P$1),"") -> 8500 | C7: =IFERROR(IF($P$1<=1,"",INDEX('Account Summary'!$B$5:$B$28,$P$1-1)),"") -> 7200 | D7: =IF(OR(C7="",C7=0,B7=""),"",(B7-C7)/C7) -> 0.18055556
A8: Impressions | B8: =IFERROR(INDEX('Account Summary'!$C$5:$C$28,$P$1),"") -> 410000 | C8: =IFERROR(IF($P$1<=1,"",INDEX('Account Summary'!$C$5:$C$28,$P$1-1)),"") -> 360000 | D8: =IF(OR(C8="",C8=0,B8=""),"",(B8-C8)/C8) -> 0.13888889
A9: Clicks | B9: =IFERROR(INDEX('Account Summary'!$D$5:$D$28,$P$1),"") -> 2300 | C9: =IFERROR(IF($P$1<=1,"",INDEX('Account Summary'!$D$5:$D$28,$P$1-1)),"") -> 1980 | D9: =IF(OR(C9="",C9=0,B9=""),"",(B9-C9)/C9) -> 0.16161616
A10: CTR | B10: =IFERROR(INDEX('Account Summary'!$E$5:$E$28,$P$1),"") -> 0.0056097561 | C10: =IFERROR(IF($P$1<=1,"",INDEX('Account Summary'!$E$5:$E$28,$P$1-1)),"") -> 0.0055 | D10: =IF(OR(C10="",B10=""),"",B10-C10) -> 0.0001097561
A11: Avg CPC | B11: =IFERROR(INDEX('Account Summary'!$F$5:$F$28,$P$1),"") -> 3.6956522 | C11: =IFERROR(IF($P$1<=1,"",INDEX('Account Summary'!$F$5:$F$28,$P$1-1)),"") -> 3.6363636 | D11: =IF(OR(C11="",C11=0,B11=""),"",(B11-C11)/C11) -> 0.016304348
A12: CPM | B12: =IFERROR(INDEX('Account Summary'!$G$5:$G$28,$P$1),"") -> 20.731707 | C12: =IFERROR(IF($P$1<=1,"",INDEX('Account Summary'!$G$5:$G$28,$P$1-1)),"") -> 20 | D12: =IF(OR(C12="",C12=0,B12=""),"",(B12-C12)/C12) -> 0.036585366
A13: Leads | B13: =IFERROR(INDEX('Account Summary'!$H$5:$H$28,$P$1),"") -> 63 | C13: =IFERROR(IF($P$1<=1,"",INDEX('Account Summary'!$H$5:$H$28,$P$1-1)),"") -> 52 | D13: =IF(OR(C13="",C13=0,B13=""),"",(B13-C13)/C13) -> 0.21153846
A14: Cost / Lead | B14: =IFERROR(INDEX('Account Summary'!$I$5:$I$28,$P$1),"") -> 134.92063 | C14: =IFERROR(IF($P$1<=1,"",INDEX('Account Summary'!$I$5:$I$28,$P$1-1)),"") -> 138.46154 | D14: =IF(OR(C14="",C14=0,B14=""),"",(B14-C14)/C14) -> -0.025573192
A15: Lead Rate | B15: =IFERROR(INDEX('Account Summary'!$J$5:$J$28,$P$1),"") -> 0.027391304 | C15: =IFERROR(IF($P$1<=1,"",INDEX('Account Summary'!$J$5:$J$28,$P$1-1)),"") -> 0.026262626 | D15: =IF(OR(C15="",B15=""),"",B15-C15) -> 0.0011286781
A16: Engagement Rate | B16: =IFERROR(INDEX('Account Summary'!$K$5:$K$28,$P$1),"") -> 0.021 | C16: =IFERROR(IF($P$1<=1,"",INDEX('Account Summary'!$K$5:$K$28,$P$1-1)),"") -> 0.02 | D16: =IF(OR(C16="",B16=""),"",B16-C16) -> 0.001
A18: Read it lead-first. Spend up is fine if leads keep pace and cost per lead holds. If CPM or CPC jump while leads stay flat, your audience or creative is tiring. Rate metrics show the change in percentage points.

Sheet Month-on-Month
A1: Month-on-Month
A2: Each metric shows the month's actual value and the change versus the prior month. Volume metrics change in %, rate metrics in percentage points. Blank rows are months not filled yet.
A4: Month | B4: Spend | D4: Impressions | F4: Clicks | H4: CTR | J4: Avg CPC | L4: Leads | N4: Cost / Lead | P4: Engagement Rate
B5: This month | C5: vs prev | D5: This month | E5: vs prev | F5: This month | G5: vs prev | H5: This month | I5: vs prev (pp) | J5: This month | K5: vs prev | L5: This month | M5: vs prev | N5: This month | O5: vs prev | P5: This month | Q5: vs prev (pp)
A6: ='Account Summary'!A5 -> Month 1 | B6: =IF('Account Summary'!B5="","",'Account Summary'!B5) -> 6000 | C6: ="n/a" -> n/a | D6: =IF('Account Summary'!C5="","",'Account Summary'!C5) -> 320000 | E6: ="n/a" -> n/a | F6: =IF('Account Summary'!D5="","",'Account Summary'!D5) -> 1600 | G6: ="n/a" -> n/a | H6: =IF('Account Summary'!E5="","",'Account Summary'!E5) -> 0.005 | I6: ="n/a" -> n/a | J6: =IF('Account Summary'!F5="","",'Account Summary'!F5) -> 3.75 | K6: ="n/a" -> n/a | L6: =IF('Account Summary'!H5="","",'Account Summary'!H5) -> 40 | M6: ="n/a" -> n/a | N6: =IF('Account Summary'!I5="","",'Account Summary'!I5) -> 150 | O6: ="n/a" -> n/a | P6: =IF('Account Summary'!K5="","",'Account Summary'!K5) -> 0.018 | Q6: ="n/a" -> n/a
A7: ='Account Summary'!A6 -> Month 2 | B7: =IF('Account Summary'!B6="","",'Account Summary'!B6) -> 7200 | C7: =IF(OR('Account Summary'!B6="",'Account Summary'!B5="",'Account Summary'!B5=0),"",('Account Summary'!B6-'Account Summary'!B5)/'Account Summary'!B5) -> 0.2 | D7: =IF('Account Summary'!C6="","",'Account Summary'!C6) -> 360000 | E7: =IF(OR('Account Summary'!C6="",'Account Summary'!C5="",'Account Summary'!C5=0),"",('Account Summary'!C6-'Account Summary'!C5)/'Account Summary'!C5) -> 0.125 | F7: =IF('Account Summary'!D6="","",'Account Summary'!D6) -> 1980 | G7: =IF(OR('Account Summary'!D6="",'Account Summary'!D5="",'Account Summary'!D5=0),"",('Account Summary'!D6-'Account Summary'!D5)/'Account Summary'!D5) -> 0.2375 | H7: =IF('Account Summary'!E6="","",'Account Summary'!E6) -> 0.0055 | I7: =IF(OR('Account Summary'!E6="",'Account Summary'!E5=""),"",'Account Summary'!E6-'Account Summary'!E5) -> 0.0005 | J7: =IF('Account Summary'!F6="","",'Account Summary'!F6) -> 3.6363636 | K7: =IF(OR('Account Summary'!F6="",'Account Summary'!F5="",'Account Summary'!F5=0),"",('Account Summary'!F6-'Account Summary'!F5)/'Account Summary'!F5) -> -0.03030303 | L7: =IF('Account Summary'!H6="","",'Account Summary'!H6) -> 52 | M7: =IF(OR('Account Summary'!H6="",'Account Summary'!H5="",'Account Summary'!H5=0),"",('Account Summary'!H6-'Account Summary'!H5)/'Account Summary'!H5) -> 0.3 | N7: =IF('Account Summary'!I6="","",'Account Summary'!I6) -> 138.46154 | O7: =IF(OR('Account Summary'!I6="",'Account Summary'!I5="",'Account Summary'!I5=0),"",('Account Summary'!I6-'Account Summary'!I5)/'Account Summary'!I5) -> -0.076923077 | P7: =IF('Account Summary'!K6="","",'Account Summary'!K6) -> 0.02 | Q7: =IF(OR('Account Summary'!K6="",'Account Summary'!K5=""),"",'Account Summary'!K6-'Account Summary'!K5) -> 0.002
A8: ='Account Summary'!A7 -> Month 3 | B8: =IF('Account Summary'!B7="","",'Account Summary'!B7) -> 8500 | C8: =IF(OR('Account Summary'!B7="",'Account Summary'!B6="",'Account Summary'!B6=0),"",('Account Summary'!B7-'Account Summary'!B6)/'Account Summary'!B6) -> 0.18055556 | D8: =IF('Account Summary'!C7="","",'Account Summary'!C7) -> 410000 | E8: =IF(OR('Account Summary'!C7="",'Account Summary'!C6="",'Account Summary'!C6=0),"",('Account Summary'!C7-'Account Summary'!C6)/'Account Summary'!C6) -> 0.13888889 | F8: =IF('Account Summary'!D7="","",'Account Summary'!D7) -> 2300 | G8: =IF(OR('Account Summary'!D7="",'Account Summary'!D6="",'Account Summary'!D6=0),"",('Account Summary'!D7-'Account Summary'!D6)/'Account Summary'!D6) -> 0.16161616 | H8: =IF('Account Summary'!E7="","",'Account Summary'!E7) -> 0.0056097561 | I8: =IF(OR('Account Summary'!E7="",'Account Summary'!E6=""),"",'Account Summary'!E7-'Account Summary'!E6) -> 0.0001097561 | J8: =IF('Account Summary'!F7="","",'Account Summary'!F7) -> 3.6956522 | K8: =IF(OR('Account Summary'!F7="",'Account Summary'!F6="",'Account Summary'!F6=0),"",('Account Summary'!F7-'Account Summary'!F6)/'Account Summary'!F6) -> 0.016304348 | L8: =IF('Account Summary'!H7="","",'Account Summary'!H7) -> 63 | M8: =IF(OR('Account Summary'!H7="",'Account Summary'!H6="",'Account Summary'!H6=0),"",('Account Summary'!H7-'Account Summary'!H6)/'Account Summary'!H6) -> 0.21153846 | N8: =IF('Account Summary'!I7="","",'Account Summary'!I7) -> 134.92063 | O8: =IF(OR('Account Summary'!I7="",'Account Summary'!I6="",'Account Summary'!I6=0),"",('Account Summary'!I7-'Account Summary'!I6)/'Account Summary'!I6) -> -0.025573192 | P8: =IF('Account Summary'!K7="","",'Account Summary'!K7) -> 0.021 | Q8: =IF(OR('Account Summary'!K7="",'Account Summary'!K6=""),"",'Account Summary'!K7-'Account Summary'!K6) -> 0.001
A9: ='Account Summary'!A8 -> Month 4 | B9: =IF('Account Summary'!B8="","",'Account Summary'!B8) | C9: =IF(OR('Account Summary'!B8="",'Account Summary'!B7="",'Account Summary'!B7=0),"",('Account Summary'!B8-'Account Summary'!B7)/'Account Summary'!B7) | D9: =IF('Account Summary'!C8="","",'Account Summary'!C8) | E9: =IF(OR('Account Summary'!C8="",'Account Summary'!C7="",'Account Summary'!C7=0),"",('Account Summary'!C8-'Account Summary'!C7)/'Account Summary'!C7) | F9: =IF('Account Summary'!D8="","",'Account Summary'!D8) | G9: =IF(OR('Account Summary'!D8="",'Account Summary'!D7="",'Account Summary'!D7=0),"",('Account Summary'!D8-'Account Summary'!D7)/'Account Summary'!D7) | H9: =IF('Account Summary'!E8="","",'Account Summary'!E8) | I9: =IF(OR('Account Summary'!E8="",'Account Summary'!E7=""),"",'Account Summary'!E8-'Account Summary'!E7) | J9: =IF('Account Summary'!F8="","",'Account Summary'!F8) | K9: =IF(OR('Account Summary'!F8="",'Account Summary'!F7="",'Account Summary'!F7=0),"",('Account Summary'!F8-'Account Summary'!F7)/'Account Summary'!F7) | L9: =IF('Account Summary'!H8="","",'Account Summary'!H8) | M9: =IF(OR('Account Summary'!H8="",'Account Summary'!H7="",'Account Summary'!H7=0),"",('Account Summary'!H8-'Account Summary'!H7)/'Account Summary'!H7) | N9: =IF('Account Summary'!I8="","",'Account Summary'!I8) | O9: =IF(OR('Account Summary'!I8="",'Account Summary'!I7="",'Account Summary'!I7=0),"",('Account Summary'!I8-'Account Summary'!I7)/'Account Summary'!I7) | P9: =IF('Account Summary'!K8="","",'Account Summary'!K8) | Q9: =IF(OR('Account Summary'!K8="",'Account Summary'!K7=""),"",'Account Summary'!K8-'Account Summary'!K7)
A10: ='Account Summary'!A9 -> Month 5 | B10: =IF('Account Summary'!B9="","",'Account Summary'!B9) | C10: =IF(OR('Account Summary'!B9="",'Account Summary'!B8="",'Account Summary'!B8=0),"",('Account Summary'!B9-'Account Summary'!B8)/'Account Summary'!B8) | D10: =IF('Account Summary'!C9="","",'Account Summary'!C9) | E10: =IF(OR('Account Summary'!C9="",'Account Summary'!C8="",'Account Summary'!C8=0),"",('Account Summary'!C9-'Account Summary'!C8)/'Account Summary'!C8) | F10: =IF('Account Summary'!D9="","",'Account Summary'!D9) | G10: =IF(OR('Account Summary'!D9="",'Account Summary'!D8="",'Account Summary'!D8=0),"",('Account Summary'!D9-'Account Summary'!D8)/'Account Summary'!D8) | H10: =IF('Account Summary'!E9="","",'Account Summary'!E9) | I10: =IF(OR('Account Summary'!E9="",'Account Summary'!E8=""),"",'Account Summary'!E9-'Account Summary'!E8) | J10: =IF('Account Summary'!F9="","",'Account Summary'!F9) | K10: =IF(OR('Account Summary'!F9="",'Account Summary'!F8="",'Account Summary'!F8=0),"",('Account Summary'!F9-'Account Summary'!F8)/'Account Summary'!F8) | L10: =IF('Account Summary'!H9="","",'Account Summary'!H9) | M10: =IF(OR('Account Summary'!H9="",'Account Summary'!H8="",'Account Summary'!H8=0),"",('Account Summary'!H9-'Account Summary'!H8)/'Account Summary'!H8) | N10: =IF('Account Summary'!I9="","",'Account Summary'!I9) | O10: =IF(OR('Account Summary'!I9="",'Account Summary'!I8="",'Account Summary'!I8=0),"",('Account Summary'!I9-'Account Summary'!I8)/'Account Summary'!I8) | P10: =IF('Account Summary'!K9="","",'Account Summary'!K9) | Q10: =IF(OR('Account Summary'!K9="",'Account Summary'!K8=""),"",'Account Summary'!K9-'Account Summary'!K8)
A11: ='Account Summary'!A10 -> Month 6 | B11: =IF('Account Summary'!B10="","",'Account Summary'!B10) | C11: =IF(OR('Account Summary'!B10="",'Account Summary'!B9="",'Account Summary'!B9=0),"",('Account Summary'!B10-'Account Summary'!B9)/'Account Summary'!B9) | D11: =IF('Account Summary'!C10="","",'Account Summary'!C10) | E11: =IF(OR('Account Summary'!C10="",'Account Summary'!C9="",'Account Summary'!C9=0),"",('Account Summary'!C10-'Account Summary'!C9)/'Account Summary'!C9) | F11: =IF('Account Summary'!D10="","",'Account Summary'!D10) | G11: =IF(OR('Account Summary'!D10="",'Account Summary'!D9="",'Account Summary'!D9=0),"",('Account Summary'!D10-'Account Summary'!D9)/'Account Summary'!D9) | H11: =IF('Account Summary'!E10="","",'Account Summary'!E10) | I11: =IF(OR('Account Summary'!E10="",'Account Summary'!E9=""),"",'Account Summary'!E10-'Account Summary'!E9) | J11: =IF('Account Summary'!F10="","",'Account Summary'!F10) | K11: =IF(OR('Account Summary'!F10="",'Account Summary'!F9="",'Account Summary'!F9=0),"",('Account Summary'!F10-'Account Summary'!F9)/'Account Summary'!F9) | L11: =IF('Account Summary'!H10="","",'Account Summary'!H10) | M11: =IF(OR('Account Summary'!H10="",'Account Summary'!H9="",'Account Summary'!H9=0),"",('Account Summary'!H10-'Account Summary'!H9)/'Account Summary'!H9) | N11: =IF('Account Summary'!I10="","",'Account Summary'!I10) | O11: =IF(OR('Account Summary'!I10="",'Account Summary'!I9="",'Account Summary'!I9=0),"",('Account Summary'!I10-'Account Summary'!I9)/'Account Summary'!I9) | P11: =IF('Account Summary'!K10="","",'Account Summary'!K10) | Q11: =IF(OR('Account Summary'!K10="",'Account Summary'!K9=""),"",'Account Summary'!K10-'Account Summary'!K9)
A12: ='Account Summary'!A11 -> Month 7 | B12: =IF('Account Summary'!B11="","",'Account Summary'!B11) | C12: =IF(OR('Account Summary'!B11="",'Account Summary'!B10="",'Account Summary'!B10=0),"",('Account Summary'!B11-'Account Summary'!B10)/'Account Summary'!B10) | D12: =IF('Account Summary'!C11="","",'Account Summary'!C11) | E12: =IF(OR('Account Summary'!C11="",'Account Summary'!C10="",'Account Summary'!C10=0),"",('Account Summary'!C11-'Account Summary'!C10)/'Account Summary'!C10) | F12: =IF('Account Summary'!D11="","",'Account Summary'!D11) | G12: =IF(OR('Account Summary'!D11="",'Account Summary'!D10="",'Account Summary'!D10=0),"",('Account Summary'!D11-'Account Summary'!D10)/'Account Summary'!D10) | H12: =IF('Account Summary'!E11="","",'Account Summary'!E11) | I12: =IF(OR('Account Summary'!E11="",'Account Summary'!E10=""),"",'Account Summary'!E11-'Account Summary'!E10) | J12: =IF('Account Summary'!F11="","",'Account Summary'!F11) | K12: =IF(OR('Account Summary'!F11="",'Account Summary'!F10="",'Account Summary'!F10=0),"",('Account Summary'!F11-'Account Summary'!F10)/'Account Summary'!F10) | L12: =IF('Account Summary'!H11="","",'Account Summary'!H11) | M12: =IF(OR('Account Summary'!H11="",'Account Summary'!H10="",'Account Summary'!H10=0),"",('Account Summary'!H11-'Account Summary'!H10)/'Account Summary'!H10) | N12: =IF('Account Summary'!I11="","",'Account Summary'!I11) | O12: =IF(OR('Account Summary'!I11="",'Account Summary'!I10="",'Account Summary'!I10=0),"",('Account Summary'!I11-'Account Summary'!I10)/'Account Summary'!I10) | P12: =IF('Account Summary'!K11="","",'Account Summary'!K11) | Q12: =IF(OR('Account Summary'!K11="",'Account Summary'!K10=""),"",'Account Summary'!K11-'Account Summary'!K10)
A13: ='Account Summary'!A12 -> Month 8 | B13: =IF('Account Summary'!B12="","",'Account Summary'!B12) | C13: =IF(OR('Account Summary'!B12="",'Account Summary'!B11="",'Account Summary'!B11=0),"",('Account Summary'!B12-'Account Summary'!B11)/'Account Summary'!B11) | D13: =IF('Account Summary'!C12="","",'Account Summary'!C12) | E13: =IF(OR('Account Summary'!C12="",'Account Summary'!C11="",'Account Summary'!C11=0),"",('Account Summary'!C12-'Account Summary'!C11)/'Account Summary'!C11) | F13: =IF('Account Summary'!D12="","",'Account Summary'!D12) | G13: =IF(OR('Account Summary'!D12="",'Account Summary'!D11="",'Account Summary'!D11=0),"",('Account Summary'!D12-'Account Summary'!D11)/'Account Summary'!D11) | H13: =IF('Account Summary'!E12="","",'Account Summary'!E12) | I13: =IF(OR('Account Summary'!E12="",'Account Summary'!E11=""),"",'Account Summary'!E12-'Account Summary'!E11) | J13: =IF('Account Summary'!F12="","",'Account Summary'!F12) | K13: =IF(OR('Account Summary'!F12="",'Account Summary'!F11="",'Account Summary'!F11=0),"",('Account Summary'!F12-'Account Summary'!F11)/'Account Summary'!F11) | L13: =IF('Account Summary'!H12="","",'Account Summary'!H12) | M13: =IF(OR('Account Summary'!H12="",'Account Summary'!H11="",'Account Summary'!H11=0),"",('Account Summary'!H12-'Account Summary'!H11)/'Account Summary'!H11) | N13: =IF('Account Summary'!I12="","",'Account Summary'!I12) | O13: =IF(OR('Account Summary'!I12="",'Account Summary'!I11="",'Account Summary'!I11=0),"",('Account Summary'!I12-'Account Summary'!I11)/'Account Summary'!I11) | P13: =IF('Account Summary'!K12="","",'Account Summary'!K12) | Q13: =IF(OR('Account Summary'!K12="",'Account Summary'!K11=""),"",'Account Summary'!K12-'Account Summary'!K11)
A14: ='Account Summary'!A13 -> Month 9 | B14: =IF('Account Summary'!B13="","",'Account Summary'!B13) | C14: =IF(OR('Account Summary'!B13="",'Account Summary'!B12="",'Account Summary'!B12=0),"",('Account Summary'!B13-'Account Summary'!B12)/'Account Summary'!B12) | D14: =IF('Account Summary'!C13="","",'Account Summary'!C13) | E14: =IF(OR('Account Summary'!C13="",'Account Summary'!C12="",'Account Summary'!C12=0),"",('Account Summary'!C13-'Account Summary'!C12)/'Account Summary'!C12) | F14: =IF('Account Summary'!D13="","",'Account Summary'!D13) | G14: =IF(OR('Account Summary'!D13="",'Account Summary'!D12="",'Account Summary'!D12=0),"",('Account Summary'!D13-'Account Summary'!D12)/'Account Summary'!D12) | H14: =IF('Account Summary'!E13="","",'Account Summary'!E13) | I14: =IF(OR('Account Summary'!E13="",'Account Summary'!E12=""),"",'Account Summary'!E13-'Account Summary'!E12) | J14: =IF('Account Summary'!F13="","",'Account Summary'!F13) | K14: =IF(OR('Account Summary'!F13="",'Account Summary'!F12="",'Account Summary'!F12=0),"",('Account Summary'!F13-'Account Summary'!F12)/'Account Summary'!F12) | L14: =IF('Account Summary'!H13="","",'Account Summary'!H13) | M14: =IF(OR('Account Summary'!H13="",'Account Summary'!H12="",'Account Summary'!H12=0),"",('Account Summary'!H13-'Account Summary'!H12)/'Account Summary'!H12) | N14: =IF('Account Summary'!I13="","",'Account Summary'!I13) | O14: =IF(OR('Account Summary'!I13="",'Account Summary'!I12="",'Account Summary'!I12=0),"",('Account Summary'!I13-'Account Summary'!I12)/'Account Summary'!I12) | P14: =IF('Account Summary'!K13="","",'Account Summary'!K13) | Q14: =IF(OR('Account Summary'!K13="",'Account Summary'!K12=""),"",'Account Summary'!K13-'Account Summary'!K12)
A15: ='Account Summary'!A14 -> Month 10 | B15: =IF('Account Summary'!B14="","",'Account Summary'!B14) | C15: =IF(OR('Account Summary'!B14="",'Account Summary'!B13="",'Account Summary'!B13=0),"",('Account Summary'!B14-'Account Summary'!B13)/'Account Summary'!B13) | D15: =IF('Account Summary'!C14="","",'Account Summary'!C14) | E15: =IF(OR('Account Summary'!C14="",'Account Summary'!C13="",'Account Summary'!C13=0),"",('Account Summary'!C14-'Account Summary'!C13)/'Account Summary'!C13) | F15: =IF('Account Summary'!D14="","",'Account Summary'!D14) | G15: =IF(OR('Account Summary'!D14="",'Account Summary'!D13="",'Account Summary'!D13=0),"",('Account Summary'!D14-'Account Summary'!D13)/'Account Summary'!D13) | H15: =IF('Account Summary'!E14="","",'Account Summary'!E14) | I15: =IF(OR('Account Summary'!E14="",'Account Summary'!E13=""),"",'Account Summary'!E14-'Account Summary'!E13) | J15: =IF('Account Summary'!F14="","",'Account Summary'!F14) | K15: =IF(OR('Account Summary'!F14="",'Account Summary'!F13="",'Account Summary'!F13=0),"",('Account Summary'!F14-'Account Summary'!F13)/'Account Summary'!F13) | L15: =IF('Account Summary'!H14="","",'Account Summary'!H14) | M15: =IF(OR('Account Summary'!H14="",'Account Summary'!H13="",'Account Summary'!H13=0),"",('Account Summary'!H14-'Account Summary'!H13)/'Account Summary'!H13) | N15: =IF('Account Summary'!I14="","",'Account Summary'!I14) | O15: =IF(OR('Account Summary'!I14="",'Account Summary'!I13="",'Account Summary'!I13=0),"",('Account Summary'!I14-'Account Summary'!I13)/'Account Summary'!I13) | P15: =IF('Account Summary'!K14="","",'Account Summary'!K14) | Q15: =IF(OR('Account Summary'!K14="",'Account Summary'!K13=""),"",'Account Summary'!K14-'Account Summary'!K13)
A16: ='Account Summary'!A15 -> Month 11 | B16: =IF('Account Summary'!B15="","",'Account Summary'!B15) | C16: =IF(OR('Account Summary'!B15="",'Account Summary'!B14="",'Account Summary'!B14=0),"",('Account Summary'!B15-'Account Summary'!B14)/'Account Summary'!B14) | D16: =IF('Account Summary'!C15="","",'Account Summary'!C15) | E16: =IF(OR('Account Summary'!C15="",'Account Summary'!C14="",'Account Summary'!C14=0),"",('Account Summary'!C15-'Account Summary'!C14)/'Account Summary'!C14) | F16: =IF('Account Summary'!D15="","",'Account Summary'!D15) | G16: =IF(OR('Account Summary'!D15="",'Account Summary'!D14="",'Account Summary'!D14=0),"",('Account Summary'!D15-'Account Summary'!D14)/'Account Summary'!D14) | H16: =IF('Account Summary'!E15="","",'Account Summary'!E15) | I16: =IF(OR('Account Summary'!E15="",'Account Summary'!E14=""),"",'Account Summary'!E15-'Account Summary'!E14) | J16: =IF('Account Summary'!F15="","",'Account Summary'!F15) | K16: =IF(OR('Account Summary'!F15="",'Account Summary'!F14="",'Account Summary'!F14=0),"",('Account Summary'!F15-'Account Summary'!F14)/'Account Summary'!F14) | L16: =IF('Account Summary'!H15="","",'Account Summary'!H15) | M16: =IF(OR('Account Summary'!H15="",'Account Summary'!H14="",'Account Summary'!H14=0),"",('Account Summary'!H15-'Account Summary'!H14)/'Account Summary'!H14) | N16: =IF('Account Summary'!I15="","",'Account Summary'!I15) | O16: =IF(OR('Account Summary'!I15="",'Account Summary'!I14="",'Account Summary'!I14=0),"",('Account Summary'!I15-'Account Summary'!I14)/'Account Summary'!I14) | P16: =IF('Account Summary'!K15="","",'Account Summary'!K15) | Q16: =IF(OR('Account Summary'!K15="",'Account Summary'!K14=""),"",'Account Summary'!K15-'Account Summary'!K14)
A17: ='Account Summary'!A16 -> Month 12 | B17: =IF('Account Summary'!B16="","",'Account Summary'!B16) | C17: =IF(OR('Account Summary'!B16="",'Account Summary'!B15="",'Account Summary'!B15=0),"",('Account Summary'!B16-'Account Summary'!B15)/'Account Summary'!B15) | D17: =IF('Account Summary'!C16="","",'Account Summary'!C16) | E17: =IF(OR('Account Summary'!C16="",'Account Summary'!C15="",'Account Summary'!C15=0),"",('Account Summary'!C16-'Account Summary'!C15)/'Account Summary'!C15) | F17: =IF('Account Summary'!D16="","",'Account Summary'!D16) | G17: =IF(OR('Account Summary'!D16="",'Account Summary'!D15="",'Account Summary'!D15=0),"",('Account Summary'!D16-'Account Summary'!D15)/'Account Summary'!D15) | H17: =IF('Account Summary'!E16="","",'Account Summary'!E16) | I17: =IF(OR('Account Summary'!E16="",'Account Summary'!E15=""),"",'Account Summary'!E16-'Account Summary'!E15) | J17: =IF('Account Summary'!F16="","",'Account Summary'!F16) | K17: =IF(OR('Account Summary'!F16="",'Account Summary'!F15="",'Account Summary'!F15=0),"",('Account Summary'!F16-'Account Summary'!F15)/'Account Summary'!F15) | L17: =IF('Account Summary'!H16="","",'Account Summary'!H16) | M17: =IF(OR('Account Summary'!H16="",'Account Summary'!H15="",'Account Summary'!H15=0),"",('Account Summary'!H16-'Account Summary'!H15)/'Account Summary'!H15) | N17: =IF('Account Summary'!I16="","",'Account Summary'!I16) | O17: =IF(OR('Account Summary'!I16="",'Account Summary'!I15="",'Account Summary'!I15=0),"",('Account Summary'!I16-'Account Summary'!I15)/'Account Summary'!I15) | P17: =IF('Account Summary'!K16="","",'Account Summary'!K16) | Q17: =IF(OR('Account Summary'!K16="",'Account Summary'!K15=""),"",'Account Summary'!K16-'Account Summary'!K15)
A18: ='Account Summary'!A17 -> Month 13 | B18: =IF('Account Summary'!B17="","",'Account Summary'!B17) | C18: =IF(OR('Account Summary'!B17="",'Account Summary'!B16="",'Account Summary'!B16=0),"",('Account Summary'!B17-'Account Summary'!B16)/'Account Summary'!B16) | D18: =IF('Account Summary'!C17="","",'Account Summary'!C17) | E18: =IF(OR('Account Summary'!C17="",'Account Summary'!C16="",'Account Summary'!C16=0),"",('Account Summary'!C17-'Account Summary'!C16)/'Account Summary'!C16) | F18: =IF('Account Summary'!D17="","",'Account Summary'!D17) | G18: =IF(OR('Account Summary'!D17="",'Account Summary'!D16="",'Account Summary'!D16=0),"",('Account Summary'!D17-'Account Summary'!D16)/'Account Summary'!D16) | H18: =IF('Account Summary'!E17="","",'Account Summary'!E17) | I18: =IF(OR('Account Summary'!E17="",'Account Summary'!E16=""),"",'Account Summary'!E17-'Account Summary'!E16) | J18: =IF('Account Summary'!F17="","",'Account Summary'!F17) | K18: =IF(OR('Account Summary'!F17="",'Account Summary'!F16="",'Account Summary'!F16=0),"",('Account Summary'!F17-'Account Summary'!F16)/'Account Summary'!F16) | L18: =IF('Account Summary'!H17="","",'Account Summary'!H17) | M18: =IF(OR('Account Summary'!H17="",'Account Summary'!H16="",'Account Summary'!H16=0),"",('Account Summary'!H17-'Account Summary'!H16)/'Account Summary'!H16) | N18: =IF('Account Summary'!I17="","",'Account Summary'!I17) | O18: =IF(OR('Account Summary'!I17="",'Account Summary'!I16="",'Account Summary'!I16=0),"",('Account Summary'!I17-'Account Summary'!I16)/'Account Summary'!I16) | P18: =IF('Account Summary'!K17="","",'Account Summary'!K17) | Q18: =IF(OR('Account Summary'!K17="",'Account Summary'!K16=""),"",'Account Summary'!K17-'Account Summary'!K16)
... A29: ='Account Summary'!A28 -> Month 24 | B29: =IF('Account Summary'!B28="","",'Account Summary'!B28) | C29: =IF(OR('Account Summary'!B28="",'Account Summary'!B27="",'Account Summary'!B27=0),"",('Account Summary'!B28-'Account Summary'!B27)/'Account Summary'!B27) | D29: =IF('Account Summary'!C28="","",'Account Summary'!C28) | E29: =IF(OR('Account Summary'!C28="",'Account Summary'!C27="",'Account Summary'!C27=0),"",('Account Summary'!C28-'Account Summary'!C27)/'Account Summary'!C27) | F29: =IF('Account Summary'!D28="","",'Account Summary'!D28) | G29: =IF(OR('Account Summary'!D28="",'Account Summary'!D27="",'Account Summary'!D27=0),"",('Account Summary'!D28-'Account Summary'!D27)/'Account Summary'!D27) | H29: =IF('Account Summary'!E28="","",'Account Summary'!E28) | I29: =IF(OR('Account Summary'!E28="",'Account Summary'!E27=""),"",'Account Summary'!E28-'Account Summary'!E27) | J29: =IF('Account Summary'!F28="","",'Account Summary'!F28) | K29: =IF(OR('Account Summary'!F28="",'Account Summary'!F27="",'Account Summary'!F27=0),"",('Account Summary'!F28-'Account Summary'!F27)/'Account Summary'!F27) | L29: =IF('Account Summary'!H28="","",'Account Summary'!H28) | M29: =IF(OR('Account Summary'!H28="",'Account Summary'!H27="",'Account Summary'!H27=0),"",('Account Summary'!H28-'Account Summary'!H27)/'Account Summary'!H27) | N29: =IF('Account Summary'!I28="","",'Account Summary'!I28) | O29: =IF(OR('Account Summary'!I28="",'Account Summary'!I27="",'Account Summary'!I27=0),"",('Account Summary'!I28-'Account Summary'!I27)/'Account Summary'!I27) | P29: =IF('Account Summary'!K28="","",'Account Summary'!K28) | Q29: =IF(OR('Account Summary'!K28="",'Account Summary'!K27=""),"",'Account Summary'!K28-'Account Summary'!K27)
A31: Note: green is up, red is down on the change columns. For Avg CPC and Cost / Lead, down is the good direction even though it prints red. Empty rows are months you have not filled yet.

Sheet By Campaign
A1: By Campaign
A2: One row per campaign per month. Blue cells are inputs (Leads from Campaign Manager). CTR, CPC, cost per lead, and lead rate are formulas. The Flag warns when spend earns no leads.
A4: Month | B4: Campaign | C4: Campaign Group | D4: Objective | E4: Impressions | F4: Clicks | G4: CTR | H4: Avg CPC | I4: Spend | J4: Leads | K4: Cost / Lead | L4: Lead Rate | M4: Engagement Rate | N4: Flag
A5: Month 3 | B5: Lead Gen - Product A | C5: Group 1 | D5: Lead Generation | E5: 90000 | F5: 520 | G5: =IF(OR(E5="",E5=0),"",F5/E5) -> 0.0057777778 | H5: =IF(OR(F5="",F5=0),"",I5/F5) -> 4.6153846 | I5: 2400 | J5: 28 | K5: =IF(OR(J5="",J5=0),"",I5/J5) -> 85.714286 | L5: =IF(OR(F5="",F5=0),"",J5/F5) -> 0.053846154 | M5: 0.022 | N5: =IF(AND(I5>0,N(J5)=0),"No leads",IF(AND(G5<>"",G5<0.004),"Low CTR",""))
A6: Month 3 | B6: Website Visits - Product B | C6: Group 2 | D6: Website Visits | E6: 110000 | F6: 700 | G6: =IF(OR(E6="",E6=0),"",F6/E6) -> 0.0063636364 | H6: =IF(OR(F6="",F6=0),"",I6/F6) -> 3 | I6: 2100 | J6: 12 | K6: =IF(OR(J6="",J6=0),"",I6/J6) -> 175 | L6: =IF(OR(F6="",F6=0),"",J6/F6) -> 0.017142857 | M6: 0.018 | N6: =IF(AND(I6>0,N(J6)=0),"No leads",IF(AND(G6<>"",G6<0.004),"Low CTR",""))
A7: Month 3 | B7: Engagement - Thought Leadership | C7: Brand | D7: Engagement | E7: 140000 | F7: 600 | G7: =IF(OR(E7="",E7=0),"",F7/E7) -> 0.0042857143 | H7: =IF(OR(F7="",F7=0),"",I7/F7) -> 2.5 | I7: 1500 | J7: 4 | K7: =IF(OR(J7="",J7=0),"",I7/J7) -> 375 | L7: =IF(OR(F7="",F7=0),"",J7/F7) -> 0.0066666667 | M7: 0.03 | N7: =IF(AND(I7>0,N(J7)=0),"No leads",IF(AND(G7<>"",G7<0.004),"Low CTR",""))
A8: Month 3 | B8: Video - Brand Story | C8: Brand | D8: Video Views | E8: 180000 | F8: 300 | G8: =IF(OR(E8="",E8=0),"",F8/E8) -> 0.0016666667 | H8: =IF(OR(F8="",F8=0),"",I8/F8) -> 4 | I8: 1200 | J8: 0 | K8: =IF(OR(J8="",J8=0),"",I8/J8) | L8: =IF(OR(F8="",F8=0),"",J8/F8) -> 0 | M8: 0.015 | N8: =IF(AND(I8>0,N(J8)=0),"No leads",IF(AND(G8<>"",G8<0.004),"Low CTR","")) -> No leads
A9: Month 3 | B9: Lead Gen - Product C | C9: Group 3 | D9: Lead Generation | E9: 70000 | F9: 480 | G9: =IF(OR(E9="",E9=0),"",F9/E9) -> 0.0068571429 | H9: =IF(OR(F9="",F9=0),"",I9/F9) -> 2.7083333 | I9: 1300 | J9: 19 | K9: =IF(OR(J9="",J9=0),"",I9/J9) -> 68.421053 | L9: =IF(OR(F9="",F9=0),"",J9/F9) -> 0.039583333 | M9: 0.024 | N9: =IF(AND(I9>0,N(J9)=0),"No leads",IF(AND(G9<>"",G9<0.004),"Low CTR",""))
A11: Sort by Spend, then by Cost per Lead. A campaign with real spend and zero leads is flagged red: most often the offer or the lead form is the problem, not the audience. Engagement and Video campaigns will show few leads by design, so judge them on engagement rate and reach.

Sheet By Campaign Group
A1: By Campaign Group
A2: Spend and leads grouped by campaign group. Blue cells are inputs. Rates and share of spend are formulas.
A4: Campaign Group | B4: Impressions | C4: Clicks | D4: CTR | E4: Spend | F4: Leads | G4: Cost / Lead | H4: Lead Rate | I4: Share of Spend
A5: Group 1 | B5: 160000 | C5: 1000 | D5: =IF(OR(B5="",B5=0),"",C5/B5) -> 0.00625 | E5: 3700 | F5: 47 | G5: =IF(OR(F5="",F5=0),"",E5/F5) -> 78.723404 | H5: =IF(OR(C5="",C5=0),"",F5/C5) -> 0.047 | I5: =IF(SUM($E$5:$E$8)=0,"",E5/SUM($E$5:$E$8)) -> 0.37755102
A6: Group 2 | B6: 110000 | C6: 700 | D6: =IF(OR(B6="",B6=0),"",C6/B6) -> 0.0063636364 | E6: 2100 | F6: 12 | G6: =IF(OR(F6="",F6=0),"",E6/F6) -> 175 | H6: =IF(OR(C6="",C6=0),"",F6/C6) -> 0.017142857 | I6: =IF(SUM($E$5:$E$8)=0,"",E6/SUM($E$5:$E$8)) -> 0.21428571
A7: Group 3 | B7: 70000 | C7: 480 | D7: =IF(OR(B7="",B7=0),"",C7/B7) -> 0.0068571429 | E7: 1300 | F7: 19 | G7: =IF(OR(F7="",F7=0),"",E7/F7) -> 68.421053 | H7: =IF(OR(C7="",C7=0),"",F7/C7) -> 0.039583333 | I7: =IF(SUM($E$5:$E$8)=0,"",E7/SUM($E$5:$E$8)) -> 0.13265306
A8: Brand | B8: 320000 | C8: 900 | D8: =IF(OR(B8="",B8=0),"",C8/B8) -> 0.0028125 | E8: 2700 | F8: 4 | G8: =IF(OR(F8="",F8=0),"",E8/F8) -> 675 | H8: =IF(OR(C8="",C8=0),"",F8/C8) -> 0.0044444444 | I8: =IF(SUM($E$5:$E$8)=0,"",E8/SUM($E$5:$E$8)) -> 0.2755102
A10: Campaign groups are how you compare funnel stages or audiences fairly. Bottom-funnel lead-gen groups should carry most of the leads; brand and engagement groups carry reach. Move budget toward the groups with the lowest cost per lead.

Sheet By Objective
A1: By Objective
A2: Performance grouped by campaign objective. Blue cells are inputs. Rates and share of spend are formulas.
A4: Objective | B4: Impressions | C4: Clicks | D4: CTR | E4: Spend | F4: Leads | G4: Cost / Lead | H4: Engagement Rate | I4: Share of Spend
A5: Lead Generation | B5: 160000 | C5: 1000 | D5: =IF(OR(B5="",B5=0),"",C5/B5) -> 0.00625 | E5: 3700 | F5: 47 | G5: =IF(OR(F5="",F5=0),"",E5/F5) -> 78.723404 | H5: 0.023 | I5: =IF(SUM($E$5:$E$9)=0,"",E5/SUM($E$5:$E$9)) -> 0.39784946
A6: Website Visits | B6: 110000 | C6: 700 | D6: =IF(OR(B6="",B6=0),"",C6/B6) -> 0.0063636364 | E6: 2100 | F6: 12 | G6: =IF(OR(F6="",F6=0),"",E6/F6) -> 175 | H6: 0.018 | I6: =IF(SUM($E$5:$E$9)=0,"",E6/SUM($E$5:$E$9)) -> 0.22580645
A7: Engagement | B7: 140000 | C7: 600 | D7: =IF(OR(B7="",B7=0),"",C7/B7) -> 0.0042857143 | E7: 1500 | F7: 4 | G7: =IF(OR(F7="",F7=0),"",E7/F7) -> 375 | H7: 0.03 | I7: =IF(SUM($E$5:$E$9)=0,"",E7/SUM($E$5:$E$9)) -> 0.16129032
A8: Video Views | B8: 180000 | C8: 300 | D8: =IF(OR(B8="",B8=0),"",C8/B8) -> 0.0016666667 | E8: 1200 | F8: 0 | G8: =IF(OR(F8="",F8=0),"",E8/F8) | H8: 0.015 | I8: =IF(SUM($E$5:$E$9)=0,"",E8/SUM($E$5:$E$9)) -> 0.12903226
A9: Brand Awareness | B9: 90000 | C9: 150 | D9: =IF(OR(B9="",B9=0),"",C9/B9) -> 0.0016666667 | E9: 800 | F9: 0 | G9: =IF(OR(F9="",F9=0),"",E9/F9) | H9: 0.008 | I9: =IF(SUM($E$5:$E$9)=0,"",E9/SUM($E$5:$E$9)) -> 0.086021505
A11: Objective decides what LinkedIn optimizes for, so never compare a Brand Awareness campaign to a Lead Generation one on cost per lead. Use this tab to check that your spend mix matches your goal: if leads are the goal, most spend should sit in Lead Generation.

Sheet Engagement
A1: Engagement
A2: Social actions per campaign for the latest month. Blue cells are inputs. Engagement rate is a formula.
A4: Campaign | B4: Impressions | C4: Reactions | D4: Comments | E4: Shares | F4: Follows | G4: Video Views | H4: Total Engagements | I4: Engagement Rate
A5: Engagement - Thought Leadership | B5: 140000 | C5: 2100 | D5: 180 | E5: 260 | F5: 90 | G5: 0 | H5: 2630 | I5: =IF(OR(B5="",B5=0),"",H5/B5) -> 0.018785714
A6: Video - Brand Story | B6: 180000 | C6: 900 | D6: 40 | E6: 120 | F6: 30 | G6: 42000 | H6: 1090 | I6: =IF(OR(B6="",B6=0),"",H6/B6) -> 0.0060555556
A7: Lead Gen - Product A | B7: 90000 | C7: 300 | D7: 20 | E7: 30 | F7: 15 | G7: 0 | H7: 365 | I7: =IF(OR(B7="",B7=0),"",H7/B7) -> 0.0040555556
A8: Website Visits - Product B | B8: 110000 | C8: 250 | D8: 10 | E8: 25 | F8: 8 | G8: 0 | H8: 293 | I8: =IF(OR(B8="",B8=0),"",H8/B8) -> 0.0026636364
A10: Engagement is the early read on creative. Strong reactions and shares with weak leads usually means the hook works but the offer or form does not. Follows are a quiet win: paid campaigns that grow your page pay off long after the budget stops.

Sheet Budget Pacing
A1: Budget Pacing
A2: Are you on track to spend your budget this month. Fill the blue cells. Projection and pace are formulas.
A4: Campaign / Account | B4: Monthly Budget | C4: Days in Month | D4: Days Elapsed | E4: Spend to Date | F4: Expected to Date | G4: Projected Month-End | H4: Pace vs Budget | I4: Status
A5: Account total | B5: 9000 | C5: 30 | D5: 12 | E5: 3700 | F5: =IF(OR(B5="",C5="",C5=0),"",B5*D5/C5) -> 3600 | G5: =IF(OR(E5="",D5="",D5=0,C5=""),"",E5/D5*C5) -> 9250 | H5: =IF(OR(G5="",B5="",B5=0),"",G5/B5) -> 1.0277778 | I5: =IF(H5="","",IF(H5>1.1,"Over",IF(H5<0.9,"Under","On track"))) -> On track
A6: Lead Gen - Product A | B6: 2400 | C6: 30 | D6: 12 | E6: 1000 | F6: =IF(OR(B6="",C6="",C6=0),"",B6*D6/C6) -> 960 | G6: =IF(OR(E6="",D6="",D6=0,C6=""),"",E6/D6*C6) -> 2500 | H6: =IF(OR(G6="",B6="",B6=0),"",G6/B6) -> 1.0416667 | I6: =IF(H6="","",IF(H6>1.1,"Over",IF(H6<0.9,"Under","On track"))) -> On track
A7: Website Visits - Product B | B7: 2100 | C7: 30 | D7: 12 | E7: 820 | F7: =IF(OR(B7="",C7="",C7=0),"",B7*D7/C7) -> 840 | G7: =IF(OR(E7="",D7="",D7=0,C7=""),"",E7/D7*C7) -> 2050 | H7: =IF(OR(G7="",B7="",B7=0),"",G7/B7) -> 0.97619048 | I7: =IF(H7="","",IF(H7>1.1,"Over",IF(H7<0.9,"Under","On track"))) -> On track
A8: Brand | B8: 2700 | C8: 30 | D8: 12 | E8: 1100 | F8: =IF(OR(B8="",C8="",C8=0),"",B8*D8/C8) -> 1080 | G8: =IF(OR(E8="",D8="",D8=0,C8=""),"",E8/D8*C8) -> 2750 | H8: =IF(OR(G8="",B8="",B8=0),"",G8/B8) -> 1.0185185 | I8: =IF(H8="","",IF(H8>1.1,"Over",IF(H8<0.9,"Under","On track"))) -> On track
A10: LinkedIn underspends quietly when audiences are too narrow or bids too low. Under means it cannot find your people at your bid, not that you saved money. Widen the audience or raise the bid before the month runs out.

Sheet Flags & Fixes
A1: Flags & Fixes
A2: The LinkedIn Ads issues worth checking every month, what each means, and the fix. Replace the sample notes with what you find.
A4: Priority | B4: Flag | C4: What it means | D4: Where to check | E4: Fix
A5: High | B5: Spend with no leads | C5: Budget going out with no lead-gen forms completed. | D5: By Campaign (red flag) | E5: Shorten the lead form, sharpen the offer, or switch a weak Website Visits campaign to a Lead Gen objective.
A6: High | B6: Cost per lead too high | C6: You are paying more per lead than the lead is worth. | D6: Account Summary, By Campaign | E6: Tighten targeting, refresh creative, test a lighter form, and pause the worst campaigns.
A7: Medium | B7: Audience too narrow | C7: Reach is small and frequency climbs fast. | D7: By Campaign (impressions) | E7: Keep audiences above roughly 300k. Loosen one targeting layer at a time.
A8: Medium | B8: Creative fatigue | C8: CTR and engagement fall as the same people see the ad again. | D8: Engagement, Month-on-Month | E8: Rotate new creative every few weeks. Cap frequency.
A9: Medium | B9: Underspending | C9: LinkedIn cannot spend the budget at your bid. | D9: Budget Pacing (Under) | E9: Raise the bid or widen the audience. Check schedule and start dates.
A10: Low | B10: Objective mismatch | C10: Spend sits in the wrong objective for your goal. | D10: By Objective | E10: Move budget into Lead Generation if leads are the goal.

Sheet Definitions
A1: Definitions
A2: Plain-language meaning of every metric in this workbook.
A4: Metric | B4: What it means | C4: Good direction
A5: Spend | B5: Total amount spent on LinkedIn Ads in the period. | C5: Match to budget
A6: Impressions | B6: How often your ads were shown. | C6: Higher with intent
A7: Clicks | B7: Total clicks, including social actions and landing-page clicks. | C7: Higher
A8: CTR | B8: Click-through rate. Clicks divided by impressions. LinkedIn runs lower than search. | C8: Higher
A9: Avg CPC | B9: Average cost per click. Spend divided by clicks. | C9: Lower
A10: CPM | B10: Cost per thousand impressions. LinkedIn runs high here. | C10: Lower
A11: Leads | B11: Lead-gen form leads. Filled by hand from Campaign Manager or your CRM. | C11: Higher
A12: Cost / Lead | B12: Spend divided by leads. The headline efficiency number. | C12: Lower
A13: Lead Rate | B13: Leads divided by clicks. | C13: Higher
A14: Engagement Rate | B14: Clicks plus social actions divided by impressions. | C14: Higher
A15: Conversions | B15: Website conversions LinkedIn attributes. Separate from lead-gen leads. | C15: Higher
... A17: Pace vs Budget | B17: Projected month-end spend divided by the monthly budget. | C17: Near 100%

Sheet Sources
A1: Sources
A2: Where the data comes from and how to pull it. Replace the placeholder account ID with yours.
A4: Source | B4: Account | C4: Open | D4: What you get
A5: LinkedIn Ads | B5: Account <YOUR-LINKEDIN-ADS-ID> | C5: Open | D5: Spend, impressions, clicks, CTR, CPC, CPM, conversions, engagement, by campaign, group, and objective
A6: LinkedIn lead-gen forms | B6: Campaign Manager, Account Assets | C6: Open | D6: Lead-gen form leads. Type these into the Leads column, the connector does not expose them
A7: Windsor.ai | B7: Connector that feeds Claude | C7: Open | D7: Pulls LinkedIn Ads metrics into this workbook through Claude
A8: Your CRM | B8: HubSpot, Salesforce, etc. | C8: Open | D8: Reconcile leads and lead quality against what LinkedIn reports
